MANIFEST.in
README.txt
setup.py
formas_de_pago/__init__.py
formas_de_pago/admin.py
formas_de_pago.egg-info/PKG-INFO
formas_de_pago.egg-info/SOURCES.txt
formas_de_pago.egg-info/dependency_links.txt
formas_de_pago.egg-info/top_level.txt
formas_de_pago/forms/__init__.py
formas_de_pago/forms/ceca.py
formas_de_pago/integrations/__init__.py
formas_de_pago/integrations/ceca_integration.py
formas_de_pago/models/__init__.py
formas_de_pago/models/ceca.py
formas_de_pago/templates/billing/ceca.html