Metadata-Version: 1.0
Name: formas-de-pago
Version: 0.0.4
Summary: Métodos de pago adicionales.
Home-page: http://www.o2w.es/
Author: José Sánchez Moreno
Author-email: jose@o2w.es
License: LICENSE.txt
Platform: UNKNOWN
